uic_package/__init__.py
uic_package/removeLabel.py
uranium_image_cleanup-1.0.0.dist-info/METADATA
uranium_image_cleanup-1.0.0.dist-info/WHEEL
uranium_image_cleanup-1.0.0.dist-info/entry_points.txt
uranium_image_cleanup-1.0.0.dist-info/top_level.txt
uranium_image_cleanup-1.0.0.dist-info/RECORD
