Metadata-Version: 2.1
Name: uranium-image-cleanup
Version: 1.0.0
Summary: Remove text/noise from grayscale uranium photos
Author: 4120 Industries
Author-email: schmaltz.6@wright.edu
License: MIT
Project-URL: Source, https://github.com/brienschmaltz/uranium_image_cleanup
Keywords: image processing filtering
Platform: UNKNOWN
Classifier: Development Status :: 5 - Production/Stable
Classifier: License :: OSI Approved :: MIT License
Classifier: Programming Language :: Python :: 3.7
Requires-Python: >=2.7, <4
Requires-Dist: tqdm
Requires-Dist: opencv-python
Requires-Dist: numpy
Requires-Dist: pillow
